consmodel/__init__.py
consmodel/ac_sim.py
consmodel/base_model.py
consmodel/bs_sim.py
consmodel/cons_sim.py
consmodel/ev_sim.py
consmodel/hp_sim.py
consmodel/pv_sim.py
consmodel/utils/__init__.py
consmodel/utils/st_types.py
consmodel/utils/tariffsys_utils.py
consmodel/utils/utils.py
consmodel-0.2.3.dist-info/LICENCE.txt
consmodel-0.2.3.dist-info/METADATA
consmodel-0.2.3.dist-info/WHEEL
consmodel-0.2.3.dist-info/top_level.txt
consmodel-0.2.3.dist-info/RECORD
