Metadata-Version: 2.2
Name: consmodel
Version: 0.2.3
Summary: The library aims to provide a simple way to create individual consumer loads, generation.
Home-page: https://github.com/blazdob/consmodel
Author: Blaž Dobravec
Author-email: blaz@dobravec.si
Project-URL: Bug Tracker, https://github.com/blazdob/consmodel/issue
Classifier: Programming Language :: Python :: 3
Classifier: License :: OSI Approved :: MIT License
Classifier: Operating System :: OS Independent
Requires-Python: >=3.6
License-File: LICENCE.txt
Requires-Dist: setuptools>=42
Requires-Dist: retry_requests>=2.0.0
Requires-Dist: openmeteo_requests>=1.1.0
Requires-Dist: requests_cache>=1.1.0
Requires-Dist: pvlib>=0.9.1
Requires-Dist: pandas>=1.5.2
Requires-Dist: numpy>=1.22.4
Requires-Dist: tzfpy>=0.15.1
Requires-Dist: meteostat>=1.6.5
Requires-Dist: scipy>=1.10.0
Requires-Dist: hplib==1.9
Requires-Dist: numba>=0.54.0
Dynamic: author
Dynamic: author-email
Dynamic: classifier
Dynamic: description
Dynamic: description-content-type
Dynamic: home-page
Dynamic: project-url
Dynamic: requires-dist
Dynamic: requires-python
Dynamic: summary
